cmake-build-release/distlock
generated/proto/distlock_pb2.py
generated/proto/distlock_pb2_grpc.py
run_once.py
run_once-0.4.2.dist-info/entry_points.txt
run_once-0.4.2.dist-info/LICENSE
run_once-0.4.2.dist-info/WHEEL
run_once-0.4.2.dist-info/METADATA
run_once-0.4.2.dist-info/RECORD
